odoo/addons/hr_timesheet_sheet_autodraft_project/README.rst
odoo/addons/hr_timesheet_sheet_autodraft_project/__init__.py
odoo/addons/hr_timesheet_sheet_autodraft_project/__manifest__.py
odoo/addons/hr_timesheet_sheet_autodraft_project/i18n/es.po
odoo/addons/hr_timesheet_sheet_autodraft_project/i18n/hr_timesheet_sheet_autodraft_project.pot
odoo/addons/hr_timesheet_sheet_autodraft_project/i18n/it.po
odoo/addons/hr_timesheet_sheet_autodraft_project/models/__init__.py
odoo/addons/hr_timesheet_sheet_autodraft_project/models/account_analytic_line.py
odoo/addons/hr_timesheet_sheet_autodraft_project/readme/CONTRIBUTORS.rst
odoo/addons/hr_timesheet_sheet_autodraft_project/readme/DESCRIPTION.rst
odoo/addons/hr_timesheet_sheet_autodraft_project/static/description/icon.png
odoo/addons/hr_timesheet_sheet_autodraft_project/static/description/index.html
odoo/addons/hr_timesheet_sheet_autodraft_project/tests/__init__.py
odoo/addons/hr_timesheet_sheet_autodraft_project/tests/test_hr_timesheet_sheet_autodraft_project.py
odoo13_addon_hr_timesheet_sheet_autodraft_project-13.0.1.0.1.dev9.dist-info/METADATA
odoo13_addon_hr_timesheet_sheet_autodraft_project-13.0.1.0.1.dev9.dist-info/WHEEL
odoo13_addon_hr_timesheet_sheet_autodraft_project-13.0.1.0.1.dev9.dist-info/top_level.txt
odoo13_addon_hr_timesheet_sheet_autodraft_project-13.0.1.0.1.dev9.dist-info/RECORD
