Metadata-Version: 2.1
Name: odoo13-addon-hr-timesheet-sheet-autodraft-project
Version: 13.0.1.0.1.dev9
Summary: Support per-project Timesheet Sheets auto-drafting.
Home-page: https://github.com/OCA/timesheet
Author: CorporateHub, Odoo Community Association (OCA)
Author-email: support@odoo-community.org
License: AGPL-3
Platform: UNKNOWN
Classifier: Programming Language :: Python
Classifier: Framework :: Odoo
Classifier: Framework :: Odoo :: 13.0
Classifier: License :: OSI Approved :: GNU Affero General Public License v3
Requires-Python: >=3.5
Requires-Dist: odoo13-addon-hr-timesheet-sheet
Requires-Dist: odoo13-addon-hr-timesheet-sheet-autodraft
Requires-Dist: odoo13-addon-hr-timesheet-sheet-policy-project-manager
Requires-Dist: odoo <13.1dev,>=13.0a
